__init__.py
cehrgpt/__init__.py
cehrgpt/cehrgpt_args.py
cehrgpt/gpt_utils.py
cehrgpt/analysis/__init__.py
cehrgpt/analysis/htn_treatment_pathway.py
cehrgpt/analysis/irregularity.py
cehrgpt/analysis/privacy/__init__.py
cehrgpt/analysis/privacy/attribute_inference.py
cehrgpt/analysis/privacy/attribute_inference_config.yml
cehrgpt/analysis/privacy/member_inference.py
cehrgpt/analysis/privacy/nearest_neighbor_inference.py
cehrgpt/analysis/privacy/reid_inference.py
cehrgpt/analysis/privacy/utils.py
cehrgpt/analysis/treatment_pathway/__init__.py
cehrgpt/analysis/treatment_pathway/depression_treatment_pathway.py
cehrgpt/analysis/treatment_pathway/diabetes_treatment_pathway.py
cehrgpt/analysis/treatment_pathway/htn_treatment_pathway.py
cehrgpt/analysis/treatment_pathway/treatment_pathway.py
cehrgpt/data/__init__.py
cehrgpt/data/cehrgpt_data_processor.py
cehrgpt/data/hf_cehrgpt_dataset.py
cehrgpt/data/hf_cehrgpt_dataset_collator.py
cehrgpt/data/hf_cehrgpt_dataset_mapping.py
cehrgpt/data/sample_packing_sampler.py
cehrgpt/generation/__init__.py
cehrgpt/generation/cehrgpt_conditional_generation.py
cehrgpt/generation/chatgpt_generation.py
cehrgpt/generation/generate_batch_hf_gpt_sequence.py
cehrgpt/generation/omop_converter_batch.py
cehrgpt/generation/omop_entity.py
cehrgpt/models/__init__.py
cehrgpt/models/activations.py
cehrgpt/models/config.py
cehrgpt/models/gpt2.py
cehrgpt/models/hf_cehrgpt.py
cehrgpt/models/hf_modeling_outputs.py
cehrgpt/models/pretrained_embeddings.py
cehrgpt/models/special_tokens.py
cehrgpt/models/tokenization_hf_cehrgpt.py
cehrgpt/omop/__init__.py
cehrgpt/omop/condition_era.py
cehrgpt/omop/observation_period.py
cehrgpt/omop/omop_argparse.py
cehrgpt/omop/omop_table_builder.py
cehrgpt/omop/ontology.py
cehrgpt/omop/sample_omop_tables.py
cehrgpt/omop/queries/__init__.py
cehrgpt/omop/queries/condition_era.py
cehrgpt/omop/queries/observation_period.py
cehrgpt/runners/__init__.py
cehrgpt/runners/data_utils.py
cehrgpt/runners/gpt_runner_util.py
cehrgpt-0.1.6.post4.dist-info/licenses/LICENSE
cehrgpt-0.1.6.post4.dist-info/METADATA
cehrgpt-0.1.6.post4.dist-info/WHEEL
cehrgpt-0.1.6.post4.dist-info/top_level.txt
cehrgpt-0.1.6.post4.dist-info/RECORD
