Metadata-Version: 2.4
Name: cehrgpt
Version: 0.1.6.post4
Summary: CEHR-GPT: Generating Electronic Health Records with Chronological Patient Timelines
Author-email: Chao Pang <chaopang229@gmail.com>, Xinzhuo Jiang <xj2193@cumc.columbia.edu>, Krishna Kalluri <kk3326@cumc.columbia.edu>, Elise Minto <em3697@cumc.columbia.edu>, Jason Patterson <jp3477@cumc.columbia.edu>, Nishanth Parameshwar Pavinkurve <np2689@cumc.columbia.edu>, Karthik Natarajan <kn2174@cumc.columbia.edu>
License: MIT License
Classifier: Development Status :: 5 - Production/Stable
Classifier: Intended Audience :: Developers
Classifier: Intended Audience :: Science/Research
Classifier: License :: OSI Approved :: MIT License
Classifier: Programming Language :: Python :: 3
Requires-Python: >=3.10.0
License-File: LICENSE
Requires-Dist: cehrbert==1.4.9
Requires-Dist: cehrbert_data==0.1.1
Requires-Dist: openai==1.54.3
Requires-Dist: optuna==4.0.0
Requires-Dist: transformers==4.44.1
Requires-Dist: tokenizers==0.19.0
Requires-Dist: peft==0.10.0
Requires-Dist: lightgbm
Requires-Dist: polars
Provides-Extra: dev
Requires-Dist: pre-commit; extra == "dev"
Requires-Dist: pytest; extra == "dev"
Requires-Dist: pytest-cov; extra == "dev"
Requires-Dist: pytest-subtests; extra == "dev"
Requires-Dist: rootutils; extra == "dev"
Requires-Dist: hypothesis; extra == "dev"
Requires-Dist: black; extra == "dev"
Provides-Extra: flash-attn
Requires-Dist: flash_attn; extra == "flash-attn"
Dynamic: license-file
